willow_exiftool/__init__.py
willow_exiftool/stripexif.py
willow_exiftool-0.1.dist-info/LICENSE
willow_exiftool-0.1.dist-info/METADATA
willow_exiftool-0.1.dist-info/WHEEL
willow_exiftool-0.1.dist-info/top_level.txt
willow_exiftool-0.1.dist-info/RECORD
