Metadata-Version: 2.1
Name: willow_exiftool
Version: 0.1
Summary: ExifTool optimizer for Willow
Maintainer-email: The Developer Society <studio@dev.ngo>
Project-URL: Homepage, https://github.com/developersociety/willow-exiftool
Classifier: Intended Audience :: Developers
Classifier: License :: OSI Approved :: BSD License
Classifier: Operating System :: OS Independent
Classifier: Programming Language :: Python
Classifier: Programming Language :: Python :: 3
Classifier: Programming Language :: Python :: 3.8
Classifier: Programming Language :: Python :: 3.9
Classifier: Programming Language :: Python :: 3.10
Classifier: Programming Language :: Python :: 3.11
Classifier: Programming Language :: Python :: 3.12
Requires-Python: >=3.8
License-File: LICENSE
Requires-Dist: Willow >=1.6.0
